pydantic_dynamo/__init__.py
pydantic_dynamo/constants.py
pydantic_dynamo/exceptions.py
pydantic_dynamo/models.py
pydantic_dynamo/repository.py
pydantic_dynamo/utils.py
pydantic_dynamo/v2/__init__.py
pydantic_dynamo/v2/models.py
pydantic_dynamo/v2/repository.py
pydantic_dynamo/v2/sync_repository.py
pydantic_dynamo/v2/utils.py
pydantic_dynamo/v2/write_once.py
pydantic_dynamo-0.4.2.dist-info/LICENSE
pydantic_dynamo-0.4.2.dist-info/METADATA
pydantic_dynamo-0.4.2.dist-info/WHEEL
pydantic_dynamo-0.4.2.dist-info/RECORD
