Metadata-Version: 2.1
Name: pydantic-dynamo
Version: 0.4.2
Summary: 
Home-page: https://github.com/david-a-jetter/pydantic-dynamo
Author: David Jetter
Author-email: davidajetter@gmail.com
Requires-Python: >=3.9,<4.0
Classifier: Programming Language :: Python :: 3
Classifier: Programming Language :: Python :: 3.9
Classifier: Programming Language :: Python :: 3.10
Classifier: Programming Language :: Python :: 3.11
Requires-Dist: aioboto3 (>=11.3.0,<12.0.0)
Requires-Dist: pydantic (>=1.10.5,<2.0.0)
